__init__.py
dire.py
dire-0.1.3.dist-info/LICENSE
dire-0.1.3.dist-info/METADATA
dire-0.1.3.dist-info/WHEEL
dire-0.1.3.dist-info/top_level.txt
dire-0.1.3.dist-info/RECORD
