Metadata-Version: 2.1
Name: dire
Version: 0.1.3
Summary: Python equivalent of Perl's warn and die functions
Home-page: https://github.com/kyclark/dire
Author: Ken Youens-Clark
Author-email: kyclark@gmail.com
License: UNKNOWN
Platform: UNKNOWN
Classifier: Programming Language :: Python :: 3
Classifier: License :: OSI Approved :: MIT License
Classifier: Operating System :: OS Independent
